cogent3_ete3/__init__.py
cogent3_ete3/interconvert.py
cogent3_ete3/style.py
cogent3_ete3-2025.7.3.dist-info/entry_points.txt
cogent3_ete3-2025.7.3.dist-info/licenses/LICENSE
cogent3_ete3-2025.7.3.dist-info/WHEEL
cogent3_ete3-2025.7.3.dist-info/METADATA
cogent3_ete3-2025.7.3.dist-info/RECORD
