Metadata-Version: 2.4
Name: cogent3-ete3
Version: 2025.7.3
Summary: cogent3 plugin for ete3
Keywords: biology,genomics,statistics,phylogeny,evolution,bioinformatics
Author-email: Yapeng Lang <u7181074@anu.edu.au>
Requires-Python: >=3.11,<3.14
Classifier: Development Status :: 2 - Pre-Alpha
Classifier: Intended Audience :: Science/Research
Classifier: License :: OSI Approved :: BSD License
Classifier: Topic :: Scientific/Engineering :: Bio-Informatics
Classifier: Topic :: Software Development :: Libraries :: Python Modules
Classifier: Operating System :: OS Independent
Classifier: Programming Language :: Python :: 3.11
Classifier: Programming Language :: Python :: 3.12
Classifier: Programming Language :: Python :: 3.13
License-File: LICENSE
Requires-Dist: cogent3>=2025.5.8a8
Requires-Dist: ete3
Requires-Dist: six
Requires-Dist: PyQt5
Requires-Dist: standard-cgi
Requires-Dist: black ; extra == "dev"
Requires-Dist: click ; extra == "dev"
Requires-Dist: docformatter ; extra == "dev"
Requires-Dist: flit ; extra == "dev"
Requires-Dist: isort ; extra == "dev"
Requires-Dist: pytest ; extra == "dev"
Requires-Dist: pytest-cov ; extra == "dev"
Requires-Dist: pytest-xdist ; extra == "dev"
Requires-Dist: nox ; extra == "dev"
Requires-Dist: pytest ; extra == "test"
Requires-Dist: pytest-cov ; extra == "test"
Requires-Dist: pytest-xdist ; extra == "test"
Requires-Dist: nox ; extra == "test"
Project-URL: Bug Tracker, https://github.com/YapengLang/cogent3-ete3/issues
Project-URL: Source Code, https://github.com/YapengLang/cogent3-ete3
Provides-Extra: dev
Provides-Extra: test
